dragonball_germany/__init__.py
dragonball_germany/py.typed
dragonball_germany/gateway/__init__.py
dragonball_germany/gateway/endpoint.py
dragonball_germany/gateway/exceptions.py
dragonball_germany/gateway/gateway.py
dragonball_germany/http_client/__init__.py
dragonball_germany/http_client/exceptions.py
dragonball_germany/http_client/http_client.py
dragonball_germany/logger/__init__.py
dragonball_germany/logger/logger.py
dragonball_germany-0.6.0.dist-info/METADATA
dragonball_germany-0.6.0.dist-info/WHEEL
dragonball_germany-0.6.0.dist-info/top_level.txt
dragonball_germany-0.6.0.dist-info/RECORD
