Metadata-Version: 2.4
Name: dragonball-germany
Version: 0.6.0
Summary: A python libary for dragonball-germany.de
Classifier: Programming Language :: Python
Classifier: Programming Language :: Python :: 3.12
Classifier: Intended Audience :: Developers
Requires-Python: >=3.12
Requires-Dist: httpx==0.27.0
Requires-Dist: pydantic==2.8.0
Provides-Extra: dev
Requires-Dist: isort==5.13.2; extra == "dev"
Requires-Dist: black==24.4.2; extra == "dev"
Requires-Dist: pytest==8.2.2; extra == "dev"
Requires-Dist: pytest-asyncio==0.23.7; extra == "dev"
Requires-Dist: fakeredis==2.23.2; extra == "dev"
Requires-Dist: pytest-mock==3.14.0; extra == "dev"
Requires-Dist: pytest-sugar==1.0.0; extra == "dev"
Requires-Dist: pre-commit==4.2.0; extra == "dev"
